importfrom/__init__.py
importfrom-1.3.0.dist-info/DESCRIPTION.rst
importfrom-1.3.0.dist-info/METADATA
importfrom-1.3.0.dist-info/RECORD
importfrom-1.3.0.dist-info/WHEEL
importfrom-1.3.0.dist-info/metadata.json
importfrom-1.3.0.dist-info/top_level.txt
